{
  "successfulVisualization": {
    "success": "true",
    "message": "Execution successful!",
    "content": {
      "timestamp": "something",
      "response": "something",
      "algorithmTime": 0,
      "parseTime": 0,
      "elapsed": 0,
      "frames": [
        {
          "lineNo": [],
          "consoleLogs": "",
          "components": [
            {
              "nodes": [1, 2, 3],
              "edges": [
                [1, 2],
                [2, 3]
              ],
              "style": {
                "nodeColors": {
                  "1": "white",
                  "2": "white",
                  "3": "white"
                },
                "edgeColors": {
                  "1": { "2": "black" },
                  "2": { "3": "black" }
                },
                "nodeLabels": {},
                "edgeLabels": {},
                "nodeShapes": {},
                "edgeShapes": {}
              }
            }
          ]
        },

        {
          "lineNo": [],
          "consoleLogs": "",
          "components": [
            {
              "nodes": [1, 2, 3],
              "edges": [
                [1, 2],
                [2, 3]
              ],
              "style": {
                "nodeColors": {
                  "1": "black",
                  "2": "white",
                  "3": "white"
                },
                "edgeColors": {
                  "1": { "2": "black" },
                  "2": { "3": "black" }
                },
                "nodeLabels": {},
                "edgeLabels": {},
                "nodeShapes": {},
                "edgeShapes": {}
              }
            }
          ]
        },
        {
          "lineNo": [],
          "consoleLogs": "",
          "components": [
            {
              "nodes": [1, 2, 3],
              "edges": [
                [1, 2],
                [2, 3]
              ],
              "style": {
                "nodeColors": {
                  "1": "black",
                  "2": "black",
                  "3": "white"
                },
                "edgeColors": {
                  "1": { "2": "white" },
                  "2": { "3": "black" }
                },
                "nodeLabels": {},
                "edgeLabels": {},
                "nodeShapes": {},
                "edgeShapes": {}
              }
            }
          ]
        },
        {
          "lineNo": [],
          "consoleLogs": "",
          "components": [
            {
              "nodes": [1, 2, 3],
              "edges": [
                [1, 2],
                [2, 3]
              ],
              "style": {
                "nodeColors": {
                  "1": "black",
                  "2": "black",
                  "3": "black"
                },
                "edgeColors": {
                  "1": { "2": "white" },
                  "2": { "3": "white" }
                }
              }
            }
          ]
        }
      ]
    }
  }
}
